Metadata-Version: 2.1
Name: motorlib
Version: 0.1.0
Summary: motor motion/trajectory simulation library
Home-page: https://gitlab.com/tiagocoutinho/motorlib
Author: Jose Tiago Macara Coutinho
Author-email: coutinhotiago@gmail.com
License: GPLv3
Keywords: motor,axis,motion,trajectory,simulation
Platform: UNKNOWN
Classifier: Development Status :: 4 - Beta
Classifier: Intended Audience :: Developers
Classifier: Intended Audience :: System Administrators
Classifier: License :: OSI Approved :: GNU General Public License v3 (GPLv3)
Classifier: Natural Language :: English
Classifier: Operating System :: POSIX
Classifier: Programming Language :: Python :: 3.5
Classifier: Programming Language :: Python :: 3.6
Classifier: Programming Language :: Python :: 3.7
Requires-Python: >=3.5
